color_tracker/__init__.py
color_tracker/tracker/__init__.py
color_tracker/tracker/tracker.py
color_tracker/utils/__init__.py
color_tracker/utils/color_range_detector.py
color_tracker/utils/helpers.py
color_tracker/utils/tracker_object.py
color_tracker/utils/visualize.py
color_tracker/utils/camera/__init__.py
color_tracker/utils/camera/base_camera.py
color_tracker/utils/camera/web_camera.py
color_tracker-0.1.1.dist-info/LICENSE
color_tracker-0.1.1.dist-info/METADATA
color_tracker-0.1.1.dist-info/WHEEL
color_tracker-0.1.1.dist-info/top_level.txt
color_tracker-0.1.1.dist-info/RECORD
