Metadata-Version: 2.1
Name: color-tracker
Version: 0.1.1
Summary: Easy to use color tracking package for object tracking based on colors
Home-page: https://github.com/gaborvecsei/Color-Tracker
Author: Gabor Vecsei
Author-email: vecseigabor.x@gmail.com
License: MIT
Keywords: color tracker vecsei gaborvecsei color_tracker
Platform: UNKNOWN
Classifier: Intended Audience :: Developers
Classifier: Intended Audience :: Education
Classifier: Intended Audience :: Science/Research
Classifier: Topic :: Education
Classifier: Topic :: Software Development
Classifier: License :: OSI Approved :: MIT License
Classifier: Programming Language :: Python :: 3
Requires-Dist: opencv-python
Requires-Dist: numpy
Requires-Dist: scipy
Requires-Dist: imageio
